wafaHell/__init__.py
wafaHell/logger.py
wafaHell/middleware.py
wafaHell/model.py
wafaHell/rateLimiter.py
wafaHell/teste.py
wafaHell/utils.py
wafahell-0.2.0.dist-info/licenses/LICENSE
wafahell-0.2.0.dist-info/METADATA
wafahell-0.2.0.dist-info/WHEEL
wafahell-0.2.0.dist-info/top_level.txt
wafahell-0.2.0.dist-info/RECORD
