Metadata-Version: 2.4
Name: wafaHell
Version: 0.2.0
Summary: Middleware WAF to Flask
Author-email: Yago Martins <yagomartins30@gmail.com>
License: MIT License
Classifier: Programming Language :: Python :: 3
Classifier: Framework :: Flask
Classifier: License :: OSI Approved :: MIT License
Classifier: Operating System :: OS Independent
Requires-Python: >=3.9
License-File: LICENSE
Requires-Dist: Flask>=2.0
Dynamic: license-file
